dnscatz/__init__.py
dnscatz/catz2nsd.py
dnscatz/zones2catz.py
dnscatz-0.1.0.dist-info/entry_points.txt
dnscatz-0.1.0.dist-info/LICENSE
dnscatz-0.1.0.dist-info/WHEEL
dnscatz-0.1.0.dist-info/METADATA
dnscatz-0.1.0.dist-info/RECORD
