Metadata-Version: 2.1
Name: dnscatz
Version: 0.1.0
Summary: DNS Catalog Zones Tools
License: BSD-2
Author: Jakob Schlyter
Author-email: jakob@kirei.se
Requires-Python: >=3.9,<4.0
Classifier: License :: Other/Proprietary License
Classifier: Programming Language :: Python :: 3
Classifier: Programming Language :: Python :: 3.9
Classifier: Programming Language :: Python :: 3.10
Requires-Dist: PyYAML (>=6.0,<7.0)
Requires-Dist: dnspython (>=2.2.0,<3.0.0)
